markdown_environments/__init__.py
markdown_environments/captioned_figure.py
markdown_environments/cited_blockquote.py
markdown_environments/div.py
markdown_environments/dropdown.py
markdown_environments/thms.py
markdown_environments/utils.py
markdown_environments-1.9.7.dist-info/METADATA
markdown_environments-1.9.7.dist-info/WHEEL
markdown_environments-1.9.7.dist-info/RECORD
