Metadata-Version: 2.4
Name: markdown-environments
Version: 1.9.7
Summary: Highly customizable extensions for Python-Markdown in the style of LaTeX environments/theorems
Project-URL: Homepage, https://github.com/AnonymousRand/python_markdown_environments
Project-URL: Documentation, https://python-markdown-environments.readthedocs.io
Project-URL: Issues, https://github.com/AnonymousRand/python_markdown_environments/issues
Author: AnonymousRand
License-Expression: MIT
Classifier: Development Status :: 5 - Production/Stable
Classifier: License :: OSI Approved :: MIT License
Classifier: Operating System :: OS Independent
Classifier: Programming Language :: Python
Classifier: Programming Language :: Python :: 3.10
Classifier: Programming Language :: Python :: 3.11
Classifier: Programming Language :: Python :: 3.12
Classifier: Programming Language :: Python :: Implementation :: CPython
Classifier: Programming Language :: Python :: Implementation :: PyPy
Requires-Python: ~=3.10
Requires-Dist: beautifulsoup4~=4.12.3
Requires-Dist: markdown~=3.7
